multivar_hypergeom/__init__.py
multivar_hypergeom/__main__.py
multivar_hypergeom/cli.py
multivar_hypergeom/multivar_hypergeom.py
multivar_hypergeom-0.0.1.dist-info/AUTHORS.rst
multivar_hypergeom-0.0.1.dist-info/LICENSE
multivar_hypergeom-0.0.1.dist-info/METADATA
multivar_hypergeom-0.0.1.dist-info/WHEEL
multivar_hypergeom-0.0.1.dist-info/entry_points.txt
multivar_hypergeom-0.0.1.dist-info/top_level.txt
multivar_hypergeom-0.0.1.dist-info/RECORD
