Metadata-Version: 2.1
Name: multivar-hypergeom
Version: 0.0.1
Summary: A Python module for sampling from the Multivariate Hypergeometric distribution.
Home-page: https://github.com/smorin8674/multivar_hypergeom
Author: Sarah Morin
Author-email: smorin8674@gmail.com
License: MIT
Project-URL: Documentation, https://multivar_hypergeom.readthedocs.io/
Project-URL: Changelog, https://multivar_hypergeom.readthedocs.io/en/latest/changelog.html
Project-URL: Issue Tracker, https://github.com/smorin8674/multivar_hypergeom/issues
Platform: UNKNOWN
Classifier: Development Status :: 5 - Production/Stable
Classifier: Intended Audience :: Developers
Classifier: License :: OSI Approved :: MIT License
Classifier: Operating System :: Unix
Classifier: Operating System :: POSIX
Classifier: Operating System :: Microsoft :: Windows
Classifier: Programming Language :: Python
Classifier: Programming Language :: Python :: 3
Classifier: Programming Language :: Python :: 3.6
Classifier: Programming Language :: Python :: 3.7
Classifier: Programming Language :: Python :: 3.8
Classifier: Programming Language :: Python :: Implementation :: CPython
Classifier: Programming Language :: Python :: Implementation :: PyPy
Classifier: Topic :: Utilities
Requires-Python: >=3.6
